[
  {
    "line": 2,
    "elements": [
      {
        "start_timestamp": "2020-09-01T02:32:12.191Z",
        "before": [
          {
            "result": {
              "duration": 22401000000,
              "status": "passed"
            },
            "match": {
              "location": "stepdefinitions.Hooks.login()"
            }
          }
        ],
        "line": 50,
        "name": "US06 User List Creation",
        "description": "",
        "id": "fhcproject;us06-user-list-creation",
        "after": [
          {
            "result": {
              "duration": 783000000,
              "status": "passed"
            },
            "match": {
              "location": "stepdefinitions.Hooks.tearDown(io.cucumber.java.Scenario)"
            }
          }
        ],
        "type": "scenario",
        "keyword": "Scenario",
        "steps": [
          {
            "result": {
              "duration": 28000000,
              "status": "passed"
            },
            "line": 51,
            "name": "user go to page",
            "match": {
              "location": "stepdefinitions.US06_UserListCreationStepDefs.user_go_to_page()"
            },
            "keyword": "Given "
          },
          {
            "result": {
              "status": "passed"
            },
            "line": 52,
            "name": "USER LIST page must be accessible.",
            "match": {
              "location": "stepdefinitions.US06_UserListCreationStepDefs.user_LIST_page_must_be_accessible()"
            },
            "keyword": "Given "
          },
          {
            "result": {
              "duration": 56000000,
              "status": "passed"
            },
            "line": 53,
            "name": "ADD USER button must be executable",
            "match": {
              "location": "stepdefinitions.US06_UserListCreationStepDefs.add_USER_button_must_be_executable()"
            },
            "keyword": "Given "
          },
          {
            "result": {
              "duration": 2615000000,
              "status": "passed"
            },
            "line": 54,
            "name": "An User can not be added if all required datas is not entered validly.",
            "match": {
              "location": "stepdefinitions.US06_UserListCreationStepDefs.an_User_can_not_be_added_if_all_required_datas_is_not_entered_validly()"
            },
            "keyword": "Given "
          },
          {
            "result": {
              "duration": 4406000000,
              "status": "passed"
            },
            "line": 55,
            "name": "An User can be added if all required datas entered validly.",
            "match": {
              "location": "stepdefinitions.US06_UserListCreationStepDefs.an_User_can_be_added_if_all_required_datas_entered_validly()"
            },
            "keyword": "Given "
          },
          {
            "result": {
              "duration": 119000000,
              "status": "passed"
            },
            "line": 56,
            "name": "Check if the Alert Box works.",
            "match": {
              "location": "stepdefinitions.US06_UserListCreationStepDefs.check_if_the_Alert_Box_works()"
            },
            "keyword": "Given "
          },
          {
            "result": {
              "duration": 7756000000,
              "status": "passed"
            },
            "line": 57,
            "name": "Check if added users can be displayed on User List Table.",
            "match": {
              "location": "stepdefinitions.US06_UserListCreationStepDefs.check_if_added_users_can_be_displayed_on_User_List_Table()"
            },
            "keyword": "Given "
          }
        ],
        "tags": [
          {
            "name": "@fhcproject"
          },
          {
            "name": "@userstory06"
          }
        ]
      }
    ],
    "name": "FHCProject",
    "description": "",
    "id": "fhcproject",
    "keyword": "Feature",
    "uri": "file:src/test/resources/features/FHCProject.feature",
    "tags": [
      {
        "name": "@fhcproject",
        "type": "Tag",
        "location": {
          "line": 1,
          "column": 1
        }
      }
    ]
  }
]